{
    "root": {
        "Food and Drink": {
            "Restaurant": [{
                "Is there a good restaurant nearby?" : {
                    "gr": "Υπάρχει κάποιο καλό εστιατόριο κοντά;",
                    "it": "C'è un buon ristorante nelle vicinanze?"
                }
            }, {
                "What dish do you recommend?" : {
                    "gr": "Τι πιάτο προτείνετε;",
                    "it": "Che piatto consigli?"
                }
            }],
            "Grocery Store": {},
            "Pastry Shop": {},
            "Water Fountain": {}
        },
        "Small Talk": {
            "Weather": [{
                "The weather is nice today!": {
                    "gr": "Ο καιρός είναι ωραίος σήμερα!",
                    "it": "Il tempo è bello oggi!"
                }
            }],
            "Local Events": {},
            "Culture": {},
            "Professions": {},
            "Games": {},
            "Music": {}
        },
        "Emergency": {
            "Hospital": {},
            "Police": {}
        },
        "Transportation": {
            "Taxi": {},
            "Train": {},
            "Boat": {},
            "Airport": {}
        },
        "Housing": {
            "Hostel": {},
            "Hotel": {}
        },
        "Sightseeing": {},
        "Word Search": {}
    }
}
